{
  "updatedAt": "2025-12-21T10:38:58.813Z",
  "days": [
    {
      "name": "Maanantai",
      "isClosed": false,
      "open": "10:30",
      "close": "22:00",
      "exception": null
    },
    {
      "name": "Tiistai",
      "isClosed": false,
      "open": "10:30",
      "close": "22:00",
      "exception": null
    },
    {
      "name": "Keskiviikko",
      "isClosed": true,
      "open": null,
      "close": null,
      "exception": "Jouluaatto"
    },
    {
      "name": "Torstai",
      "isClosed": true,
      "open": null,
      "close": null,
      "exception": "Joulup채iv채"
    },
    {
      "name": "Perjantai",
      "isClosed": false,
      "open": "13:00",
      "close": "02:00",
      "exception": "Tapaninp채iv채"
    },
    {
      "name": "Lauantai",
      "isClosed": false,
      "open": "13:00",
      "close": "02:00",
      "exception": null
    },
    {
      "name": "Sunnuntai",
      "isClosed": false,
      "open": "13:00",
      "close": "22:00",
      "exception": null
    }
  ]
}